raster_codecs/__init__.py
raster_codecs/config.py
raster_codecs/deflate.py
raster_codecs/jpeg.py
raster_codecs-0.1.0.dist-info/METADATA
raster_codecs-0.1.0.dist-info/WHEEL
raster_codecs-0.1.0.dist-info/top_level.txt
raster_codecs-0.1.0.dist-info/RECORD
